BayesX1/__init__.py
bayesx1-0.0.1.dist-info/METADATA
bayesx1-0.0.1.dist-info/WHEEL
bayesx1-0.0.1.dist-info/licenses/LICENSE
bayesx1-0.0.1.dist-info/RECORD
