Metadata-Version: 2.1
Name: BayesX1
Version: 0.0.1
Summary: A client for interacting with the BayesX1 service
Project-URL: Homepage, https://bayesx1.com
Author-email: "BayesX1, Inc." <bayesx1@proton.me>
License-File: LICENSE
Classifier: License :: OSI Approved :: Apache Software License
Classifier: Operating System :: OS Independent
Classifier: Programming Language :: Python :: 3
Requires-Python: >=3.7
